OpenSSL/SSL.py
OpenSSL/__init__.py
OpenSSL/_util.py
OpenSSL/crypto.py
OpenSSL/debug.py
OpenSSL/rand.py
OpenSSL/version.py
pyOpenSSL-24.0.0.dist-info/LICENSE
pyOpenSSL-24.0.0.dist-info/METADATA
pyOpenSSL-24.0.0.dist-info/WHEEL
pyOpenSSL-24.0.0.dist-info/top_level.txt
pyOpenSSL-24.0.0.dist-info/RECORD
